
{
    "variants": {
        "level=0": { "model": "realistic_bakery_products:block/raw_honey_shortcake" },
        "level=1": { "model": "realistic_bakery_products:block/raw_honey_shortcake_1" },
        "level=2": { "model": "realistic_bakery_products:block/raw_honey_shortcake_2" },
        "level=3": { "model": "realistic_bakery_products:block/raw_honey_shortcake_3" },
        "level=4": { "model": "realistic_bakery_products:block/raw_honey_shortcake_4" },
        "level=5": { "model": "realistic_bakery_products:block/raw_honey_shortcake_5" },
        "level=6": { "model": "realistic_bakery_products:block/raw_honey_shortcake_6" },
        "level=7": { "model": "realistic_bakery_products:block/raw_honey_cake" }
    }
}